tform/__init__.py
tform/__main__.py
tform-0.1.1.dist-info/DESCRIPTION.rst
tform-0.1.1.dist-info/METADATA
tform-0.1.1.dist-info/RECORD
tform-0.1.1.dist-info/WHEEL
tform-0.1.1.dist-info/entry_points.txt
tform-0.1.1.dist-info/metadata.json
tform-0.1.1.dist-info/top_level.txt
