Metadata-Version: 2.0
Name: tform
Version: 0.1.1
Summary: UNKNOWN
Home-page: UNKNOWN
Author: UNKNOWN
Author-email: UNKNOWN
License: UNKNOWN
Platform: UNKNOWN
Requires-Dist: PyYAML (==3.13)
Requires-Dist: certifi (>=2018)
Requires-Dist: chardet (>=3.0)
Requires-Dist: fire (==0.1.3)
Requires-Dist: idna (>=2.5)
Requires-Dist: requests (==2.21.0)
Requires-Dist: six (==1.12.0)
Requires-Dist: urllib3 (==1.24.1)
